bloom/__init__.py
bloom/pinput.py
bloom/selector.py
bloom/title.py
bloom/styles/__init__.py
bloom/styles/bg.py
bloom/styles/fg.py
bloom/styles/style.py
bloom/utils/__init__.py
bloom/utils/cursor.py
bloom_tui-0.2.0.dist-info/LICENSE
bloom_tui-0.2.0.dist-info/METADATA
bloom_tui-0.2.0.dist-info/WHEEL
bloom_tui-0.2.0.dist-info/top_level.txt
bloom_tui-0.2.0.dist-info/RECORD
