Metadata-Version: 2.2
Name: bloom-tui
Version: 0.2.0
Summary: Utility to make your terminal apps stand out.
Author-email: Piker <iker.pavcur@gmail.com>
Project-URL: Homepage, https://github.com/piker98988/colourup
Project-URL: Issues, https://github.com/piker98988/colourup/issues
Classifier: Programming Language :: Python :: 3
Classifier: License :: OSI Approved :: GNU General Public License v3 (GPLv3)
Classifier: Operating System :: OS Independent
Requires-Python: >=3.11
License-File: LICENSE
Requires-Dist: colorama>=0.4.6
Requires-Dist: getch
